setup.py
dscorenlp/DSCoreNLP.py
dscorenlp/_init_.py
dscorenlp.egg-info/PKG-INFO
dscorenlp.egg-info/SOURCES.txt
dscorenlp.egg-info/dependency_links.txt
dscorenlp.egg-info/not-zip-safe
dscorenlp.egg-info/top_level.txt