Metadata-Version: 1.0
Name: dscorenlp
Version: 0.3
Summary: Data Sentiment Core NLP
Home-page: https://github.com/VarmaHub/dscorenlp
Author: Varma G.S.
Author-email: gsvarma@protonmail.com
License: MIT
Platform: UNKNOWN
